logginglib/__init__.py
logginglib/logging.py
logginglib-0.1.1.dist-info/METADATA
logginglib-0.1.1.dist-info/WHEEL
logginglib-0.1.1.dist-info/RECORD
