Metadata-Version: 2.1
Name: logginglib
Version: 0.1.1
Summary: Evvve Platform Logging Lib
Author: Levon Yeghiazaryan
Author-email: levon@evvve.net
Requires-Python: >=3.10,<4.0
Classifier: Programming Language :: Python :: 3
Classifier: Programming Language :: Python :: 3.10
Classifier: Programming Language :: Python :: 3.11
Requires-Dist: python-json-logger (>=2.0.7,<3.0.0)
